
	{
	"pid": "unfenvc:643",
		"props": {
			
				"info:fedora/fedora-system:def/model#state": "Active"
				,
				"info:fedora/fedora-system:def/model#label": "Carolina False Vervain Photo 1"
				,
				"info:fedora/fedora-system:def/model#ownerId": "UNF Environmental Center"
				,
				"info:fedora/fedora-system:def/model#createdDate": "2014-01-21T15:28:30.882Z"
				,
				"info:fedora/fedora-system:def/view#lastModifiedDate": "2015-02-24T15:45:38.401Z"
				
		},
		"dcs": [
			
				{
				"attrs": {
					
						"id": "DC.0"
						,
						"label": "Dublin Core Record for this object"
						,
						"created": "2014-01-21T15:28:30.882Z"
						,
						"mimetype": "text/xml"
						,
						"format_uri": "http://www.openarchives.org/OAI/2.0/oai_dc/"
						,
						"size": "394"
						
					},
				"content": {
				
					"title": "Carolina False Vervain Photo 1"
					,
					"identifier": "unfenvc:643"
					
					}
				}
				,
				{
				"attrs": {
					
						"id": "DC.1"
						,
						"label": "Dublin Core Record for this object"
						,
						"created": "2014-01-21T15:28:31.377Z"
						,
						"mimetype": "text/xml"
						,
						"format_uri": "http://www.openarchives.org/OAI/2.0/oai_dc/"
						,
						"size": "626"
						
					},
				"content": {
				
					"title": "Carolina False Vervain Photo 1"
					,
					"creator": "Justin Lemmons"
					,
					"date": "2014-01-21T10:28:31-05:00"
					,
					"type": "Image"
					,
					"format": "image/jpeg"
					,
					"identifier": "unfenvc:643"
					,
					"rights": "Copyright © 2013 UNF and the UNF Environmental Center"
					
					}
				}
				,
				{
				"attrs": {
					
						"id": "DC.2"
						,
						"label": "Dublin Core Record for this object"
						,
						"created": "2014-05-16T09:22:37.129Z"
						,
						"mimetype": "text/xml"
						,
						"format_uri": "http://www.w3.org/TR/xml/"
						,
						"size": "625"
						
					},
				"content": {
				
					"title": "Carolina False Vervain Photo 1"
					,
					"creator": "Justin Lemmons"
					,
					"date": "2014-01-21T10:28:31-05:00"
					,
					"type": "Image"
					,
					"format": "image/jpg"
					,
					"identifier": "unfenvc:643"
					,
					"rights": "Copyright © 2013 UNF and the UNF Environmental Center"
					
					}
				}
				,
				{
				"attrs": {
					
						"id": "DC.3"
						,
						"label": "Dublin Core Record for this object"
						,
						"created": "2014-05-18T13:08:07.188Z"
						,
						"mimetype": "text/xml"
						,
						"format_uri": "http://www.openarchives.org/OAI/2.0/oai_dc/"
						,
						"size": "625"
						
					},
				"content": {
				
					"title": "Carolina False Vervain Photo 1"
					,
					"creator": "Justin Lemmons"
					,
					"date": "2014-01-21T10:28:31-05:00"
					,
					"type": "Image"
					,
					"format": "image/jpg"
					,
					"identifier": "unfenvc:643"
					,
					"rights": "Copyright © 2013 UNF and the UNF Environmental Center"
					
					}
				}
				,
				{
				"attrs": {
					
						"id": "DC.4"
						,
						"label": "Dublin Core Record for this object"
						,
						"created": "2014-12-16T17:11:43.043Z"
						,
						"mimetype": "text/xml"
						,
						"format_uri": "http://www.openarchives.org/OAI/2.0/oai_dc/"
						,
						"size": "626"
						
					},
				"content": {
				
					"title": "Carolina False Vervain Photo 1"
					,
					"creator": "Justin Lemmons"
					,
					"date": "2014-12-16T12:11:43-05:00"
					,
					"type": "Image"
					,
					"format": "image/jpeg"
					,
					"identifier": "unfenvc:643"
					,
					"rights": "Copyright © 2013 UNF and the UNF Environmental Center"
					
					}
				}
				,
				{
				"attrs": {
					
						"id": "DC.5"
						,
						"label": "Dublin Core Record for this object"
						,
						"created": "2015-02-11T16:29:56.114Z"
						,
						"mimetype": "text/xml"
						,
						"format_uri": "http://www.openarchives.org/OAI/2.0/oai_dc/"
						,
						"size": "626"
						
					},
				"content": {
				
					"title": "Carolina False Vervain Photo 1"
					,
					"creator": "Jason McGregor"
					,
					"date": "2015-02-11T11:29:55-05:00"
					,
					"type": "Image"
					,
					"format": "image/jpeg"
					,
					"identifier": "unfenvc:643"
					,
					"rights": "Copyright © 2013 UNF and the UNF Environmental Center"
					
					}
				}
				
		],
		"exifs": [
		
			{
			"attrs": {
			
				"id": "EXIF.0"
				,
				"label": "EXIF Data"
				,
				"created": "2014-01-21T15:28:31.467Z"
				,
				"alt_ids": "exif.xml"
				,
				"mimetype": "text/xml"
				,
				"format_uri": "http://www.w3.org/TR/xml/"
				,
				"size": "312"
				
			},
			"content": {
			
				"image_description": "No EXIF in file so this is default set."
				,
				"north_or_south_latitude": "N"
				,
				"latitude": "30, 15, 57.5634"
				,
				"east_or_west_longitude": "W"
				,
				"longitude": "81, 30, 42.5844"
				,
				"altitude": "0.0"
				
				}
			}
			
		],
		"kmls": [
		
			{
			"attrs": {
			
				"id": "KML.0"
				,
				"label": "OGC/Google KML(GPS) Data"
				,
				"created": "2014-01-21T15:28:31.564Z"
				,
				"alt_ids": "marker.kml"
				,
				"mimetype": "application/vnd.google-earth.kml+xml"
				,
				"format_uri": "http://www.opengeospatial.org/standards/kml/"
				,
				"size": "278"
				
			},
			"content": {
			
			"name": "Carolina False Vervain",
			"desc": "&lt;i&gt;Stylodon carneum&lt;/i&gt;",
			"coordinates": "-81.511829,30.265989833333,0.0"
				}
			}
			,
			{
			"attrs": {
			
				"id": "KML.1"
				,
				"label": "OGC/Google KML(GPS) Data"
				,
				"created": "2015-02-24T15:45:38.401Z"
				,
				"mimetype": "application/vnd.google-earth.kml+xml"
				,
				"format_uri": "http://www.opengeospatial.org/standards/kml/"
				,
				"size": "278"
				
			},
			"content": {
			
			"name": "Carolina False Vervain",
			"desc": "&lt;i&gt;Stylodon carneum&lt;/i&gt;",
			"coordinates": "-81.511829,30.265989833333,0.0"
				}
			}
			
		],
		"rels": [
		
			{
			"attrs": {
			
				"id": "RELS-EXT.0"
				,
				"label": "Relationships"
				,
				"created": "2014-01-21T15:28:31.049Z"
				,
				"mimetype": "application/rdf+xml"
				,
				"format_uri": "info:fedora/fedora-system:FedoraRELSExt-1.0"
				,
				"size": "152"
				
				},
			"content": {
			
				}
			}
			,
			{
			"attrs": {
			
				"id": "RELS-EXT.1"
				,
				"label": "Relationships"
				,
				"created": "2014-01-21T15:28:31.193Z"
				,
				"mimetype": "application/rdf+xml"
				,
				"format_uri": "info:fedora/fedora-system:FedoraRELSExt-1.0"
				,
				"size": "238"
				
				},
			"content": {
			
						"isitemof": "info:fedora/unfenvc:20"
					
				}
			}
			,
			{
			"attrs": {
			
				"id": "RELS-EXT.2"
				,
				"label": "Relationships"
				,
				"created": "2014-01-21T15:28:31.273Z"
				,
				"mimetype": "application/rdf+xml"
				,
				"format_uri": "info:fedora/fedora-system:FedoraRELSExt-1.0"
				,
				"size": "328"
				
				},
			"content": {
			
						"isitemof": "info:fedora/unfenvc:20"
					,
						"ispartof": "plant:518"
					
				}
			}
			
		],
		"sources": [
		
			{
			"attrs": {
			
				"id": "Source.0"
				,
				"label": "Source file"
				,
				"created": "2014-01-21T15:28:31.662Z"
				,
				"alt_ids": "Stylodon-carneum-flower.JPG"
				,
				"mimetype": "image/jpeg"
				,
				"format_uri": "http://www.jpeg.org/jpeg"
				,
				"size": "2688101"
				
				},
			"content": {
			"md5": "",
			"url": "http://ecenter.unf.edu:8080/fedora/get/unfenvc:643/Source/2014-01-21T15:28:31.662Z"
				}
			}
			,
			{
			"attrs": {
			
				"id": "Source.1"
				,
				"label": "Source file"
				,
				"created": "2014-05-15T21:59:46.660Z"
				,
				"mimetype": "image/jpg"
				,
				"format_uri": "http://www.jpeg.org/jpeg"
				,
				"size": "2688101"
				
				},
			"content": {
			"md5": "",
			"url": "http://ecenter.unf.edu:8080/fedora/get/unfenvc:643/Source/2014-05-15T21:59:46.660Z"
				}
			}
			,
			{
			"attrs": {
			
				"id": "Source.2"
				,
				"label": "Source file"
				,
				"created": "2014-12-16T15:27:21.731Z"
				,
				"mimetype": "image/jpeg"
				,
				"format_uri": "http://www.jpeg.org/jpeg"
				,
				"size": "2688101"
				
				},
			"content": {
			"md5": "",
			"url": "http://ecenter.unf.edu:8080/fedora/get/unfenvc:643/Source/2014-12-16T15:27:21.731Z"
				}
			}
			
		],
		"thumbs": [
		
			{
			"attrs": {
			
				"id": "THUMB.0"
				,
				"label": "Thumbnail of image"
				,
				"created": "2014-01-21T15:28:31.805Z"
				,
				"alt_ids": "/Volumes/data/phptemp/Stylodon-carneum-flower.JPG"
				,
				"mimetype": "image/jpeg"
				,
				"format_uri": "http://www.jpeg.org/jpeg"
				,
				"size": "70647"
				
			},
			"content": {
			"url": "http://ecenter.unf.edu:8080/fedora/get/unfenvc:643/THUMB/2014-01-21T15:28:31.805Z"
			}
			}
			,
			{
			"attrs": {
			
				"id": "THUMB.1"
				,
				"label": "Thumbnail of image"
				,
				"created": "2014-05-15T21:59:46.781Z"
				,
				"mimetype": "image/jpg"
				,
				"format_uri": "http://www.jpeg.org/jpeg"
				,
				"size": "70647"
				
			},
			"content": {
			"url": "http://ecenter.unf.edu:8080/fedora/get/unfenvc:643/THUMB/2014-05-15T21:59:46.781Z"
			}
			}
			,
			{
			"attrs": {
			
				"id": "THUMB.2"
				,
				"label": "Thumbnail of image"
				,
				"created": "2014-12-16T15:45:02.987Z"
				,
				"mimetype": "image/jpeg"
				,
				"format_uri": "http://www.jpeg.org/jpeg"
				,
				"size": "70647"
				
			},
			"content": {
			"url": "http://ecenter.unf.edu:8080/fedora/get/unfenvc:643/THUMB/2014-12-16T15:45:02.987Z"
			}
			}
			,
			{
			"attrs": {
			
				"id": "THUMB.3"
				,
				"label": "Thumbnail of image"
				,
				"created": "2014-12-17T13:51:35.086Z"
				,
				"alt_ids": "Source_thumbnail"
				,
				"mimetype": "image/jpeg"
				,
				"format_uri": "http://www.jpeg.org/jpeg"
				,
				"size": "71774"
				
			},
			"content": {
			"url": "http://ecenter.unf.edu:8080/fedora/get/unfenvc:643/THUMB/2014-12-17T13:51:35.086Z"
			}
			}
			
		]
	}
	